mb/numpy/__init__.py
mb/pandas/__init__.py
mb/plt/__init__.py
mb/plt/emb_viz.py
mb/plt/utils.py
mb/utils/__init__.py
mb/utils/pip_update.py
mb_base-1.1.19.dist-info/METADATA
mb_base-1.1.19.dist-info/WHEEL
mb_base-1.1.19.dist-info/top_level.txt
mb_base-1.1.19.dist-info/RECORD
