Metadata-Version: 2.4
Name: mb_base
Version: 1.1.19
Summary: Meta Package for mb_* packages
Author: ['Malav Bateriwala']
Requires-Python: >=3.8
Requires-Dist: mb_utils
Requires-Dist: mb_pandas
Dynamic: author
Dynamic: requires-dist
Dynamic: requires-python
Dynamic: summary
